{
  "Nichole Adshead-Bell": "/speakers/2025/nichole_adshead_bell.png",
  "Neil Adshead": "/speakers/2025/neil_adshead.png",
  "Phillips S. Baker": "/speakers/2025/phillips_s__baker.png",
  "Rob Curtis": "/speakers/2025/rob_curtis.png",
  "Daniella Dimitrov": "/speakers/2025/daniella_dimitrov.png",
  "Lisa Davis": "/speakers/2025/lisa_davis.png",
  "David Garofalo": "/speakers/2025/david_garofalo.png",
  "Matt Gordon": "/speakers/2025/matt_gordon.png",
  "Michael Gentile": "/speakers/2025/michael_gentile.png",
  "Peter Grandich": "/speakers/2025/peter_grandich.png",
  "Ed Ho": "/speakers/2025/ed_ho.png",
  "Armand MacKenzie": "/speakers/2025/armand_mackenzie.png",
  "Angelina Mehta": "/speakers/2025/angelina_mehta.png",
  "David Rhodes": "/speakers/2025/david_rhodes.png",
  "Sean Roosen": "/speakers/2025/sean_roosen.png",
  "Alexis Segal": "/speakers/2025/alexis_segal.png",
  "Elian Terner": "/speakers/2025/elian_terner.png",
  "Keith Spence": "/speakers/2025/keith_spence.png",
  "Jamie Strauss": "/speakers/2025/jamie_strauss.png",
  "Anthony Vaccaro": "/speakers/2025/anthony_vaccaro.png",
  "Maria Smirnova": "/speakers/2025/maria_smirnova.png",
  "Gary Stanley": "/speakers/2025/gary_stanley.png",
  "Heather Taylor": "/speakers/2025/heather_taylor.png",
  "Michael F. White": "/speakers/2025/michael_f__white.png",
  "Rob Weir": "/speakers/2025/rob_weir.png",
  "Alexandra Woodyer Sherron": "/speakers/2025/alexandra_woodyer_sherron.png",
  "Matthew Zolnowski": "/speakers/2025/matthew_zolnowski.png"
}